COPYING.txt
MANIFEST.in
README.txt
setup.py
archivalook/__init__.py
archivalook/forms.py
archivalook/models.py
archivalook/tools.py
archivalook/utils.py
archivalook/views.py
archivalook.egg-info/PKG-INFO
archivalook.egg-info/SOURCES.txt
archivalook.egg-info/dependency_links.txt
archivalook.egg-info/top_level.txt
archivalook/static/css/featured-media.css
archivalook/templates/archivalook/feature.html
archivalook/templates/archivalook/feature_media_sidebar.html
archivalook/templates/archivalook/recent_media.html
archivalook/templates/archivalook/root.html
archivalook/templates/archivalook/feature_displays/audio_head.html
archivalook/templates/archivalook/feature_displays/audio_primary.html
archivalook/templates/archivalook/feature_displays/audio_secondary.html
archivalook/templates/archivalook/feature_displays/default_primary.html
archivalook/templates/archivalook/feature_displays/default_secondary.html
archivalook/templates/archivalook/feature_displays/default_tertiary.html
archivalook/templates/archivalook/feature_displays/image_primary.html
archivalook/templates/archivalook/feature_displays/image_secondary.html
archivalook/templates/archivalook/feature_displays/video_head.html
archivalook/templates/archivalook/feature_displays/video_primary.html
archivalook/templates/archivalook/feature_displays/video_secondary.html
archivalook/templates/archivalook/utils/display_featured.html