Metadata-Version: 1.0
Name: archivalook
Version: 1.0
Summary: UNKNOWN
Home-page: UNKNOWN
Author: UNKNOWN
Author-email: UNKNOWN
License: AGPLv3
Platform: UNKNOWN
